distancecomputation/__init__.py
distancecomputation/cli.py
distancecomputation/functions.py
distancecomputation/py.typed
distancecomputation/requirements.txt
distancecomputation/setup.py
distance_computation-0.0.2.dist-info/LICENSE
distance_computation-0.0.2.dist-info/METADATA
distance_computation-0.0.2.dist-info/WHEEL
distance_computation-0.0.2.dist-info/RECORD
