Metadata-Version: 2.1
Name: distance-computation
Version: 0.0.2
Summary: Distance data
Home-page: https://MFStark.github.io/distance-computation
License: MIT
Author: mfiking
Author-email: mfikingas@gmail.com
Requires-Python: >=3.10,<4.0
Classifier: Development Status :: 4 - Beta
Classifier: Intended Audience :: Developers
Classifier: License :: OSI Approved :: MIT License
Classifier: Operating System :: OS Independent
Classifier: Programming Language :: Python
Classifier: Programming Language :: Python :: 3
Classifier: Programming Language :: Python :: 3.10
Classifier: Programming Language :: Python :: 3.11
Classifier: Programming Language :: Python :: 3.12
Classifier: Programming Language :: Python :: 3.7
Classifier: Programming Language :: Python :: 3.8
Classifier: Programming Language :: Python :: 3.9
Classifier: Topic :: Software Development :: Libraries :: Python Modules
Classifier: Typing :: Typed
Requires-Dist: click
Project-URL: Documentation, https://MFStark.github.io/distance-computation
Project-URL: Repository, https://github.com/MFStark/distance-computation
